starrail/__init__.py
starrail/constants.py
starrail/automation/__init__.py
starrail/automation/recorder.py
starrail/automation/config/__init__.py
starrail/automation/config/automation_config_handler.py
starrail/automation/pixel_calculator/__init__.py
starrail/automation/pixel_calculator/pixel_calculator.py
starrail/automation/pixel_calculator/resolution_detector.py
starrail/automation/units/__init__.py
starrail/automation/units/action.py
starrail/automation/units/sequence.py
starrail/bin/__init__.py
starrail/bin/loader/__init__.py
starrail/bin/loader/loader.py
starrail/bin/logs/starrail_log.txt
starrail/bin/pick/__init__.py
starrail/bin/pick/pick.py
starrail/bin/pid/get_active_pid.c
starrail/bin/pid/get_active_pid.exe
starrail/bin/scheduler/__init__.py
starrail/bin/scheduler/starrail_scheduler.py
starrail/bin/scheduler/config/__init__.py
starrail/bin/scheduler/config/starrail_schedule_config.py
starrail/config/__init__.py
starrail/config/config_handler.py
starrail/controllers/__init__.py
starrail/controllers/automation_controller.py
starrail/controllers/c_click_controller.py
starrail/controllers/star_rail_app.py
starrail/controllers/streaming_assets_controller.py
starrail/controllers/web_controller.py
starrail/controllers/webcache_controller.py
starrail/data/textfiles/disclaimer.txt
starrail/data/textfiles/webcache_explain.txt
starrail/entrypoints/__init__.py
starrail/entrypoints/entrypoint_handler.py
starrail/entrypoints/entrypoints.py
starrail/entrypoints/help_format_handler.py
starrail/exceptions/__init__.py
starrail/exceptions/exceptions.py
starrail/resources/github/banner.png
starrail/resources/github/banner_bg.png
starrail/resources/github/cli_banner_1.png
starrail/resources/github/cli_banner_2.png
starrail/resources/github/firefly_cutout.png
starrail/resources/github/readme_banner_0.png
starrail/resources/github/readme_banner_1.png
starrail/resources/github/readme_banner_2.png
starrail/resources/github/readme_banner_3.png
starrail-1.0.5.dist-info/LICENSE
starrail-1.0.5.dist-info/METADATA
starrail-1.0.5.dist-info/WHEEL
starrail-1.0.5.dist-info/entry_points.txt
starrail-1.0.5.dist-info/top_level.txt
starrail-1.0.5.dist-info/RECORD
