Metadata-Version: 2.1
Name: starrail
Version: 1.0.5
Summary: Honkai: Star Rail Command Line Tool (CLI)
Home-page: https://github.com/ReZeroE/StarRail
Author: Kevin L.
Author-email: kevinliu@vt.edu
License: MIT
Project-URL: Bug Tracker, https://github.com/ReZeroE/StarRail/issues
Classifier: Programming Language :: Python :: 3
Classifier: License :: OSI Approved :: MIT License
Classifier: Operating System :: OS Independent
Classifier: Development Status :: 1 - Planning
Requires-Python: >=3.7
License-File: LICENSE
Requires-Dist: tabulate
Requires-Dist: termcolor
Requires-Dist: pytest
Requires-Dist: psutil
Requires-Dist: pynput
Requires-Dist: pyautogui
Requires-Dist: pywin32
Requires-Dist: screeninfo
Requires-Dist: schedule
Requires-Dist: pyreadline3
